oquat/__init__.py
oquat/__main__.py
oquat/analyze_invalids.py
oquat/analyze_unknowns.py
oquat/analyze_versions.py
oquat/api.py
oquat/cli.py
oquat/large_scale_analysis.py
oquat/py.typed
oquat/templates/invalid_xrefs.md
oquat/version.py
oquat-0.1.0.dist-info/licenses/LICENSE
oquat-0.1.0.dist-info/WHEEL
oquat-0.1.0.dist-info/entry_points.txt
oquat-0.1.0.dist-info/METADATA
oquat-0.1.0.dist-info/RECORD
