Metadata-Version: 2.4
Name: oquat
Version: 0.1.0
Summary: Assess the quality of biomedical ontologies
Keywords: snekpack,cookiecutter,biomedical ontologies,ontologies,ontology,OBO Foundry,obo,OWL
Author: Charles Tapley Hoyt
Author-email: Charles Tapley Hoyt <cthoyt@gmail.com>
License-File: LICENSE
Classifier: Development Status :: 1 - Planning
Classifier: Environment :: Console
Classifier: Intended Audience :: Developers
Classifier: License :: OSI Approved :: MIT License
Classifier: Operating System :: OS Independent
Classifier: Framework :: Pytest
Classifier: Framework :: tox
Classifier: Framework :: Sphinx
Classifier: Natural Language :: English
Classifier: Programming Language :: Python
Classifier: Programming Language :: Python :: 3.10
Classifier: Programming Language :: Python :: 3.11
Classifier: Programming Language :: Python :: 3.12
Classifier: Programming Language :: Python :: 3.13
Classifier: Programming Language :: Python :: 3 :: Only
Classifier: Typing :: Typed
Requires-Dist: bioregistry>=0.12.13
Requires-Dist: click
Requires-Dist: pydantic>=2.0
Requires-Dist: pystow
Requires-Dist: requests
Requires-Dist: more-click
Requires-Dist: tabulate
Requires-Dist: jinja2
Requires-Dist: tqdm
Requires-Dist: obographs>=0.0.6
Maintainer: Charles Tapley Hoyt
Maintainer-email: Charles Tapley Hoyt <cthoyt@gmail.com>
Requires-Python: >=3.10
Project-URL: Bug Tracker, https://github.com/biopragmatics/oquat/issues
Project-URL: Documentation, https://oquat.readthedocs.io
Project-URL: Funding, https://github.com/sponsors/cthoyt
Project-URL: Homepage, https://github.com/biopragmatics/oquat
Project-URL: Repository, https://github.com/biopragmatics/oquat.git
